[
  {
    "meet_id": 162,
    "meet": "Club Time Trials June 2024",
    "date": "2024-06-03",
    "course": "SCM",
    "event": "50 Freestyle",
    "time": "41.45",
    "place": ""
  },
  {
    "meet_id": 162,
    "meet": "Club Time Trials June 2024",
    "date": "2024-06-03",
    "course": "SCM",
    "event": "100 IM",
    "time": "1:44.87",
    "place": ""
  },
  {
    "meet_id": 156,
    "meet": "Warrender End of Season SC Mee",
    "date": "2024-06-15",
    "course": "SCM",
    "event": "100 Freestyle",
    "time": "1:34.83",
    "place": "33"
  },
  {
    "meet_id": 156,
    "meet": "Warrender End of Season SC Mee",
    "date": "2024-06-15",
    "course": "SCM",
    "event": "50 Backstroke",
    "time": "44.16",
    "place": "22"
  },
  {
    "meet_id": 163,
    "meet": "Club 50m Sprints August 2024",
    "date": "2024-08-19",
    "course": "SCM",
    "event": "50 Freestyle",
    "time": "39.73",
    "place": ""
  },
  {
    "meet_id": 163,
    "meet": "Club 50m Sprints August 2024",
    "date": "2024-08-19",
    "course": "SCM",
    "event": "50 Backstroke",
    "time": "44.49",
    "place": ""
  },
  {
    "meet_id": 163,
    "meet": "Club 50m Sprints August 2024",
    "date": "2024-08-19",
    "course": "SCM",
    "event": "50 Breaststroke",
    "time": "52.28",
    "place": ""
  },
  {
    "meet_id": 163,
    "meet": "Club 50m Sprints August 2024",
    "date": "2024-08-19",
    "course": "SCM",
    "event": "50 Butterfly",
    "time": "43.93",
    "place": ""
  },
  {
    "meet_id": 166,
    "meet": "Club Time Trials September 202",
    "date": "2024-09-02",
    "course": "SCM",
    "event": "100 Freestyle",
    "time": "1:27.97",
    "place": ""
  },
  {
    "meet_id": 166,
    "meet": "Club Time Trials September 202",
    "date": "2024-09-02",
    "course": "SCM",
    "event": "50 Backstroke",
    "time": "42.22",
    "place": ""
  },
  {
    "meet_id": 161,
    "meet": "South Lanarkshire Development",
    "date": "2024-09-14",
    "course": "SCM",
    "event": "50 Breaststroke",
    "time": "49.54",
    "place": "1"
  },
  {
    "meet_id": 172,
    "meet": "South Lanarkshire Development",
    "date": "2024-10-05",
    "course": "SCM",
    "event": "100 Backstroke",
    "time": "1:33.95",
    "place": "1"
  },
  {
    "meet_id": 172,
    "meet": "South Lanarkshire Development",
    "date": "2024-10-05",
    "course": "SCM",
    "event": "100 Breaststroke",
    "time": "1:52.52",
    "place": "1"
  },
  {
    "meet_id": 173,
    "meet": "Club Time Trials October 2024",
    "date": "2024-10-12",
    "course": "SCM",
    "event": "50 Breaststroke",
    "time": "50.06",
    "place": ""
  },
  {
    "meet_id": 173,
    "meet": "Club Time Trials October 2024",
    "date": "2024-10-12",
    "course": "SCM",
    "event": "200 IM",
    "time": "3:39.59",
    "place": ""
  },
  {
    "meet_id": 170,
    "meet": "2024 WD Short Course Champions",
    "date": "2024-10-19",
    "course": "SCM",
    "event": "50 Backstroke",
    "time": "41.58",
    "place": "15"
  },
  {
    "meet_id": 170,
    "meet": "2024 WD Short Course Champions",
    "date": "2024-10-19",
    "course": "SCM",
    "event": "50 Butterfly",
    "time": "43.90",
    "place": "16"
  },
  {
    "meet_id": 183,
    "meet": "Club Time Trials November 2024",
    "date": "2024-11-04",
    "course": "SCM",
    "event": "50 Freestyle",
    "time": "36.62",
    "place": ""
  },
  {
    "meet_id": 183,
    "meet": "Club Time Trials November 2024",
    "date": "2024-11-04",
    "course": "SCM",
    "event": "100 Breaststroke",
    "time": "1:51.25",
    "place": ""
  },
  {
    "meet_id": 185,
    "meet": "South Lanarkshire Development",
    "date": "2024-11-16",
    "course": "SCM",
    "event": "100 Backstroke",
    "time": "1:32.58",
    "place": "1"
  },
  {
    "meet_id": 185,
    "meet": "South Lanarkshire Development",
    "date": "2024-11-16",
    "course": "SCM",
    "event": "100 Breaststroke",
    "time": "1:48.34",
    "place": "2"
  },
  {
    "meet_id": 186,
    "meet": "Larkhall Club Championships 20",
    "date": "2024-12-08",
    "course": "SCM",
    "event": "50 Freestyle",
    "time": "36.32",
    "place": "2"
  },
  {
    "meet_id": 186,
    "meet": "Larkhall Club Championships 20",
    "date": "2024-12-08",
    "course": "SCM",
    "event": "50 Backstroke",
    "time": "41.07",
    "place": "1"
  },
  {
    "meet_id": 186,
    "meet": "Larkhall Club Championships 20",
    "date": "2024-12-08",
    "course": "SCM",
    "event": "50 Breaststroke",
    "time": "48.83",
    "place": "2"
  },
  {
    "meet_id": 186,
    "meet": "Larkhall Club Championships 20",
    "date": "2024-12-08",
    "course": "SCM",
    "event": "50 Butterfly",
    "time": "43.37",
    "place": "2"
  },
  {
    "meet_id": 187,
    "meet": "South Lanarkshire Development",
    "date": "2025-01-18",
    "course": "SCM",
    "event": "100 Freestyle",
    "time": "1:24.03",
    "place": "1"
  },
  {
    "meet_id": 187,
    "meet": "South Lanarkshire Development",
    "date": "2025-01-18",
    "course": "SCM",
    "event": "100 Backstroke",
    "time": "1:27.38",
    "place": "1"
  },
  {
    "meet_id": 187,
    "meet": "South Lanarkshire Development",
    "date": "2025-01-18",
    "course": "SCM",
    "event": "100 Breaststroke",
    "time": "1:46.51",
    "place": "2"
  },
  {
    "meet_id": 192,
    "meet": "Scottish Schools Championships",
    "date": "2025-01-24",
    "course": "LCM",
    "event": "50 Backstroke",
    "time": "39.44",
    "place": "6"
  },
  {
    "meet_id": 192,
    "meet": "Scottish Schools Championships",
    "date": "2025-01-24",
    "course": "LCM",
    "event": "50 Backstroke",
    "time": "39.62",
    "place": "7"
  },
  {
    "meet_id": 225,
    "meet": "Club Time Trials February 2025",
    "date": "2025-02-03",
    "course": "SCM",
    "event": "50 Freestyle",
    "time": "36.13",
    "place": ""
  },
  {
    "meet_id": 225,
    "meet": "Club Time Trials February 2025",
    "date": "2025-02-03",
    "course": "SCM",
    "event": "200 Breaststroke",
    "time": "3:50.56",
    "place": ""
  },
  {
    "meet_id": 225,
    "meet": "Club Time Trials February 2025",
    "date": "2025-02-03",
    "course": "SCM",
    "event": "100 IM",
    "time": "1:32.39",
    "place": ""
  },
  {
    "meet_id": 189,
    "meet": "Hearts Fast February",
    "date": "2025-02-22",
    "course": "SCM",
    "event": "50 Freestyle",
    "time": "34.17",
    "place": "6"
  },
  {
    "meet_id": 189,
    "meet": "Hearts Fast February",
    "date": "2025-02-22",
    "course": "SCM",
    "event": "100 Backstroke",
    "time": "1:26.92",
    "place": "9"
  },
  {
    "meet_id": 189,
    "meet": "Hearts Fast February",
    "date": "2025-02-22",
    "course": "SCM",
    "event": "100 Breaststroke",
    "time": "1:43.44",
    "place": "10"
  },
  {
    "meet_id": 205,
    "meet": "2025 WD Long Course Championsh",
    "date": "2025-03-01",
    "course": "LCM",
    "event": "50 Freestyle",
    "time": "33.46",
    "place": "5"
  },
  {
    "meet_id": 205,
    "meet": "2025 WD Long Course Championsh",
    "date": "2025-03-01",
    "course": "LCM",
    "event": "50 Backstroke",
    "time": "38.48",
    "place": "4"
  },
  {
    "meet_id": 205,
    "meet": "2025 WD Long Course Championsh",
    "date": "2025-03-01",
    "course": "LCM",
    "event": "100 Backstroke",
    "time": "1:26.65",
    "place": "5"
  },
  {
    "meet_id": 205,
    "meet": "2025 WD Long Course Championsh",
    "date": "2025-03-01",
    "course": "LCM",
    "event": "50 Breaststroke",
    "time": "48.52",
    "place": "8"
  },
  {
    "meet_id": 205,
    "meet": "2025 WD Long Course Championsh",
    "date": "2025-03-01",
    "course": "LCM",
    "event": "50 Butterfly",
    "time": "44.28",
    "place": "12"
  },
  {
    "meet_id": 226,
    "meet": "Club Time Trials March 2025",
    "date": "2025-03-03",
    "course": "SCM",
    "event": "50 Backstroke",
    "time": "40.64",
    "place": ""
  },
  {
    "meet_id": 226,
    "meet": "Club Time Trials March 2025",
    "date": "2025-03-03",
    "course": "SCM",
    "event": "100 Butterfly",
    "time": "1:48.52",
    "place": ""
  },
  {
    "meet_id": 226,
    "meet": "Club Time Trials March 2025",
    "date": "2025-03-03",
    "course": "SCM",
    "event": "200 IM",
    "time": "3:14.00",
    "place": ""
  },
  {
    "meet_id": 199,
    "meet": "Dumfries Spring Splash Graded",
    "date": "2025-03-29",
    "course": "SCM",
    "event": "50 Freestyle",
    "time": "33.40",
    "place": "1"
  },
  {
    "meet_id": 199,
    "meet": "Dumfries Spring Splash Graded",
    "date": "2025-03-29",
    "course": "SCM",
    "event": "50 Backstroke",
    "time": "39.99",
    "place": "1"
  },
  {
    "meet_id": 199,
    "meet": "Dumfries Spring Splash Graded",
    "date": "2025-03-29",
    "course": "SCM",
    "event": "200 IM",
    "time": "3:16.23",
    "place": "1"
  },
  {
    "meet_id": 224,
    "meet": "Club Time Trials April 2025",
    "date": "2025-04-07",
    "course": "SCM",
    "event": "200 Freestyle",
    "time": "3:02.47",
    "place": ""
  },
  {
    "meet_id": 224,
    "meet": "Club Time Trials April 2025",
    "date": "2025-04-07",
    "course": "SCM",
    "event": "100 Backstroke",
    "time": "1:29.13",
    "place": ""
  },
  {
    "meet_id": 224,
    "meet": "Club Time Trials April 2025",
    "date": "2025-04-07",
    "course": "SCM",
    "event": "50 Butterfly",
    "time": "43.28",
    "place": ""
  },
  {
    "meet_id": 201,
    "meet": "North Ayrshire Junior Meet",
    "date": "2025-05-03",
    "course": "SCM",
    "event": "200 Freestyle",
    "time": "2:58.41",
    "place": "8"
  },
  {
    "meet_id": 201,
    "meet": "North Ayrshire Junior Meet",
    "date": "2025-05-03",
    "course": "SCM",
    "event": "100 Backstroke",
    "time": "1:23.94",
    "place": "2"
  },
  {
    "meet_id": 201,
    "meet": "North Ayrshire Junior Meet",
    "date": "2025-05-03",
    "course": "SCM",
    "event": "100 Breaststroke",
    "time": "1:50.49",
    "place": "5"
  },
  {
    "meet_id": 227,
    "meet": "Club Time Trials May 2025",
    "date": "2025-05-05",
    "course": "SCM",
    "event": "100 Freestyle",
    "time": "1:18.62",
    "place": ""
  },
  {
    "meet_id": 227,
    "meet": "Club Time Trials May 2025",
    "date": "2025-05-05",
    "course": "SCM",
    "event": "200 Backstroke",
    "time": "3:08.00",
    "place": ""
  },
  {
    "meet_id": 227,
    "meet": "Club Time Trials May 2025",
    "date": "2025-05-05",
    "course": "SCM",
    "event": "50 Breaststroke",
    "time": "50.57",
    "place": ""
  },
  {
    "meet_id": 204,
    "meet": "South Lanarkshire Development",
    "date": "2025-05-10",
    "course": "SCM",
    "event": "100 Freestyle",
    "time": "1:23.64",
    "place": "2"
  },
  {
    "meet_id": 204,
    "meet": "South Lanarkshire Development",
    "date": "2025-05-10",
    "course": "SCM",
    "event": "100 Backstroke",
    "time": "1:27.15",
    "place": "1"
  },
  {
    "meet_id": 204,
    "meet": "South Lanarkshire Development",
    "date": "2025-05-10",
    "course": "SCM",
    "event": "100 Breaststroke",
    "time": "1:49.47",
    "place": "3"
  },
  {
    "meet_id": 230,
    "meet": "Club Time Trials June 2025",
    "date": "2025-06-02",
    "course": "SCM",
    "event": "200 Freestyle",
    "time": "3:01.98",
    "place": ""
  },
  {
    "meet_id": 230,
    "meet": "Club Time Trials June 2025",
    "date": "2025-06-02",
    "course": "SCM",
    "event": "50 Breaststroke",
    "time": "48.48",
    "place": ""
  },
  {
    "meet_id": 230,
    "meet": "Club Time Trials June 2025",
    "date": "2025-06-02",
    "course": "SCM",
    "event": "100 IM",
    "time": "1:29.27",
    "place": ""
  },
  {
    "meet_id": 238,
    "meet": "Club 50m Time Trials",
    "date": "2025-08-18",
    "course": "SCM",
    "event": "50 Freestyle",
    "time": "35.10",
    "place": ""
  },
  {
    "meet_id": 238,
    "meet": "Club 50m Time Trials",
    "date": "2025-08-18",
    "course": "SCM",
    "event": "50 Backstroke",
    "time": "38.15",
    "place": ""
  },
  {
    "meet_id": 238,
    "meet": "Club 50m Time Trials",
    "date": "2025-08-18",
    "course": "SCM",
    "event": "50 Breaststroke",
    "time": "50.13",
    "place": ""
  },
  {
    "meet_id": 238,
    "meet": "Club 50m Time Trials",
    "date": "2025-08-18",
    "course": "SCM",
    "event": "50 Butterfly",
    "time": "38.43",
    "place": ""
  },
  {
    "meet_id": 237,
    "meet": "Club Time Trials September 202",
    "date": "2025-09-01",
    "course": "SCM",
    "event": "400 Freestyle",
    "time": "5:54.10",
    "place": ""
  },
  {
    "meet_id": 237,
    "meet": "Club Time Trials September 202",
    "date": "2025-09-01",
    "course": "SCM",
    "event": "100 Backstroke",
    "time": "1:20.61",
    "place": ""
  },
  {
    "meet_id": 233,
    "meet": "South Lanarkshire Development",
    "date": "2025-09-20",
    "course": "SCM",
    "event": "100 Freestyle",
    "time": "1:18.38",
    "place": "3"
  },
  {
    "meet_id": 233,
    "meet": "South Lanarkshire Development",
    "date": "2025-09-20",
    "course": "SCM",
    "event": "100 Backstroke",
    "time": "1:19.29",
    "place": "1"
  },
  {
    "meet_id": 233,
    "meet": "South Lanarkshire Development",
    "date": "2025-09-20",
    "course": "SCM",
    "event": "200 IM",
    "time": "3:04.60",
    "place": "1"
  },
  {
    "meet_id": 232,
    "meet": "Forth Valley Tridents Age Grou",
    "date": "2025-09-28",
    "course": "SCM",
    "event": "100 Freestyle",
    "time": "1:14.76",
    "place": "12"
  },
  {
    "meet_id": 232,
    "meet": "Forth Valley Tridents Age Grou",
    "date": "2025-09-28",
    "course": "SCM",
    "event": "100 Backstroke",
    "time": "1:17.85",
    "place": "4"
  },
  {
    "meet_id": 232,
    "meet": "Forth Valley Tridents Age Grou",
    "date": "2025-09-28",
    "course": "SCM",
    "event": "200 IM",
    "time": "3:04.74",
    "place": "9"
  },
  {
    "meet_id": 235,
    "meet": "South Lanarkshire Development",
    "date": "2025-10-04",
    "course": "SCM",
    "event": "100 Freestyle",
    "time": "1:15.80",
    "place": "1"
  },
  {
    "meet_id": 235,
    "meet": "South Lanarkshire Development",
    "date": "2025-10-04",
    "course": "SCM",
    "event": "100 Breaststroke",
    "time": "1:44.14",
    "place": "2"
  },
  {
    "meet_id": 235,
    "meet": "South Lanarkshire Development",
    "date": "2025-10-04",
    "course": "SCM",
    "event": "200 IM",
    "time": "3:04.66",
    "place": "2"
  },
  {
    "meet_id": 240,
    "meet": "Club Time Trials October 2025",
    "date": "2025-10-06",
    "course": "SCM",
    "event": "100 Breaststroke",
    "time": "1:45.18",
    "place": ""
  },
  {
    "meet_id": 240,
    "meet": "Club Time Trials October 2025",
    "date": "2025-10-06",
    "course": "SCM",
    "event": "400 IM",
    "time": "6:50.88",
    "place": ""
  },
  {
    "meet_id": 242,
    "meet": "southlanarkshire development m",
    "date": "2025-11-01",
    "course": "SCM",
    "event": "100 Freestyle",
    "time": "1:16.15",
    "place": "1"
  },
  {
    "meet_id": 242,
    "meet": "southlanarkshire development m",
    "date": "2025-11-01",
    "course": "SCM",
    "event": "100 Breaststroke",
    "time": "1:44.65",
    "place": "3"
  },
  {
    "meet_id": 246,
    "meet": "Club Time Trials November 2025",
    "date": "2025-11-03",
    "course": "SCM",
    "event": "800 Freestyle",
    "time": "12:29.72",
    "place": ""
  },
  {
    "meet_id": 246,
    "meet": "Club Time Trials November 2025",
    "date": "2025-11-03",
    "course": "SCM",
    "event": "50 Butterfly",
    "time": "37.20",
    "place": ""
  },
  {
    "meet_id": 241,
    "meet": "2025 WD Short Course Champions",
    "date": "2025-11-08",
    "course": "SCM",
    "event": "50 Freestyle",
    "time": "31.69",
    "place": "6"
  },
  {
    "meet_id": 241,
    "meet": "2025 WD Short Course Champions",
    "date": "2025-11-08",
    "course": "SCM",
    "event": "50 Freestyle",
    "time": "31.93",
    "place": "7"
  },
  {
    "meet_id": 241,
    "meet": "2025 WD Short Course Champions",
    "date": "2025-11-08",
    "course": "SCM",
    "event": "100 Freestyle",
    "time": "1:15.32",
    "place": "17"
  },
  {
    "meet_id": 241,
    "meet": "2025 WD Short Course Champions",
    "date": "2025-11-08",
    "course": "SCM",
    "event": "200 Backstroke",
    "time": "2:59.79",
    "place": "13"
  },
  {
    "meet_id": 241,
    "meet": "2025 WD Short Course Champions",
    "date": "2025-11-08",
    "course": "SCM",
    "event": "50 Breaststroke",
    "time": "45.93",
    "place": "12"
  },
  {
    "meet_id": 239,
    "meet": "Dumfries ASC Advent Open 2025",
    "date": "2025-11-21",
    "course": "SCM",
    "event": "100 Freestyle",
    "time": "1:16.59",
    "place": "11"
  },
  {
    "meet_id": 239,
    "meet": "Dumfries ASC Advent Open 2025",
    "date": "2025-11-21",
    "course": "SCM",
    "event": "100 Backstroke",
    "time": "1:19.28",
    "place": "3"
  },
  {
    "meet_id": 239,
    "meet": "Dumfries ASC Advent Open 2025",
    "date": "2025-11-21",
    "course": "SCM",
    "event": "200 Backstroke",
    "time": "2:48.91",
    "place": "3"
  },
  {
    "meet_id": 239,
    "meet": "Dumfries ASC Advent Open 2025",
    "date": "2025-11-21",
    "course": "SCM",
    "event": "50 Breaststroke",
    "time": "46.77",
    "place": "5"
  },
  {
    "meet_id": 239,
    "meet": "Dumfries ASC Advent Open 2025",
    "date": "2025-11-21",
    "course": "SCM",
    "event": "50 Butterfly",
    "time": "38.00",
    "place": "5"
  },
  {
    "meet_id": 245,
    "meet": "Larkhall Club Championships 20",
    "date": "2025-11-28",
    "course": "SCM",
    "event": "100 Freestyle",
    "time": "1:12.10",
    "place": "2"
  },
  {
    "meet_id": 245,
    "meet": "Larkhall Club Championships 20",
    "date": "2025-11-28",
    "course": "SCM",
    "event": "100 Backstroke",
    "time": "1:21.55",
    "place": "1"
  },
  {
    "meet_id": 245,
    "meet": "Larkhall Club Championships 20",
    "date": "2025-11-28",
    "course": "SCM",
    "event": "100 Butterfly",
    "time": "1:35.54",
    "place": "2"
  },
  {
    "meet_id": 245,
    "meet": "Larkhall Club Championships 20",
    "date": "2025-11-28",
    "course": "SCM",
    "event": "200 IM",
    "time": "3:09.51",
    "place": "2"
  },
  {
    "meet_id": 243,
    "meet": "EK Winter Invitational Meet 20",
    "date": "2025-12-07",
    "course": "SCM",
    "event": "50 Freestyle",
    "time": "32.26",
    "place": "5"
  },
  {
    "meet_id": 243,
    "meet": "EK Winter Invitational Meet 20",
    "date": "2025-12-07",
    "course": "SCM",
    "event": "100 Backstroke",
    "time": "DQ",
    "place": ""
  },
  {
    "meet_id": 243,
    "meet": "EK Winter Invitational Meet 20",
    "date": "2025-12-07",
    "course": "SCM",
    "event": "200 Backstroke",
    "time": "2:54.76",
    "place": "3"
  },
  {
    "meet_id": 247,
    "meet": "Forth Valley Tridents Open Mee",
    "date": "2026-01-17",
    "course": "SCM",
    "event": "50 Freestyle",
    "time": "31.35",
    "place": "12"
  },
  {
    "meet_id": 247,
    "meet": "Forth Valley Tridents Open Mee",
    "date": "2026-01-17",
    "course": "SCM",
    "event": "50 Backstroke",
    "time": "35.17",
    "place": "5"
  },
  {
    "meet_id": 247,
    "meet": "Forth Valley Tridents Open Mee",
    "date": "2026-01-17",
    "course": "SCM",
    "event": "100 Backstroke",
    "time": "1:17.62",
    "place": "15"
  },
  {
    "meet_id": 247,
    "meet": "Forth Valley Tridents Open Mee",
    "date": "2026-01-17",
    "course": "SCM",
    "event": "200 Backstroke",
    "time": "2:52.08",
    "place": "14"
  },
  {
    "meet_id": 253,
    "meet": "Clyde Coast Mini League",
    "date": "2026-01-24",
    "course": "SCM",
    "event": "50 Freestyle",
    "time": "32.27",
    "place": ""
  },
  {
    "meet_id": 253,
    "meet": "Clyde Coast Mini League",
    "date": "2026-01-24",
    "course": "SCM",
    "event": "50 Backstroke",
    "time": "36.90",
    "place": ""
  },
  {
    "meet_id": 249,
    "meet": "South Lanarkshire Development",
    "date": "2026-01-31",
    "course": "SCM",
    "event": "200 IM",
    "time": "2:56.82",
    "place": "2"
  },
  {
    "meet_id": 254,
    "meet": "Club Time Trials February 2026",
    "date": "2026-02-02",
    "course": "SCM",
    "event": "100 Freestyle",
    "time": "1:11.95",
    "place": ""
  },
  {
    "meet_id": 254,
    "meet": "Club Time Trials February 2026",
    "date": "2026-02-02",
    "course": "SCM",
    "event": "200 Backstroke",
    "time": "2:54.75",
    "place": ""
  },
  {
    "meet_id": 254,
    "meet": "Club Time Trials February 2026",
    "date": "2026-02-02",
    "course": "SCM",
    "event": "100 Breaststroke",
    "time": "1:48.41",
    "place": ""
  },
  {
    "meet_id": 248,
    "meet": "2026 WD Long Course Championsh",
    "date": "2026-02-07",
    "course": "LCM",
    "event": "50 Backstroke",
    "time": "35.69",
    "place": "4"
  },
  {
    "meet_id": 248,
    "meet": "2026 WD Long Course Championsh",
    "date": "2026-02-07",
    "course": "LCM",
    "event": "50 Backstroke",
    "time": "35.91",
    "place": "4"
  },
  {
    "meet_id": 248,
    "meet": "2026 WD Long Course Championsh",
    "date": "2026-02-07",
    "course": "LCM",
    "event": "100 Backstroke",
    "time": "1:18.86",
    "place": "7"
  },
  {
    "meet_id": 248,
    "meet": "2026 WD Long Course Championsh",
    "date": "2026-02-07",
    "course": "LCM",
    "event": "50 Butterfly",
    "time": "39.56",
    "place": "13"
  },
  {
    "meet_id": 250,
    "meet": "North Ayrshire 200 Meet 2026",
    "date": "2026-02-13",
    "course": "SCM",
    "event": "200 Backstroke",
    "time": "2:51.39",
    "place": "6"
  },
  {
    "meet_id": 250,
    "meet": "North Ayrshire 200 Meet 2026",
    "date": "2026-02-13",
    "course": "SCM",
    "event": "200 IM",
    "time": "3:07.17",
    "place": "9"
  },
  {
    "meet_id": 257,
    "meet": "Club Time Trials March 2026",
    "date": "2026-03-02",
    "course": "SCM",
    "event": "200 Freestyle",
    "time": "2:44.36",
    "place": ""
  },
  {
    "meet_id": 257,
    "meet": "Club Time Trials March 2026",
    "date": "2026-03-02",
    "course": "SCM",
    "event": "50 Breaststroke",
    "time": "44.98",
    "place": ""
  },
  {
    "meet_id": 257,
    "meet": "Club Time Trials March 2026",
    "date": "2026-03-02",
    "course": "SCM",
    "event": "100 Butterfly",
    "time": "1:35.97",
    "place": ""
  },
  {
    "meet_id": 262,
    "meet": "South Lanarkshire Schools 2026",
    "date": "2026-03-11",
    "course": "SCM",
    "event": "100 Freestyle",
    "time": "1:12.69",
    "place": "5"
  },
  {
    "meet_id": 262,
    "meet": "South Lanarkshire Schools 2026",
    "date": "2026-03-11",
    "course": "SCM",
    "event": "100 Backstroke",
    "time": "1:17.95",
    "place": "2"
  },
  {
    "meet_id": 262,
    "meet": "South Lanarkshire Schools 2026",
    "date": "2026-03-11",
    "course": "SCM",
    "event": "200 Backstroke",
    "time": "2:49.60",
    "place": "2"
  },
  {
    "meet_id": 255,
    "meet": "Cumbernauld Spring Open Meet 2",
    "date": "2026-03-14",
    "course": "SCM",
    "event": "200 Backstroke",
    "time": "2:46.46",
    "place": "11"
  },
  {
    "meet_id": 256,
    "meet": "2026 WD Long Course March Meet",
    "date": "2026-03-21",
    "course": "LCM",
    "event": "50 Freestyle",
    "time": "30.60",
    "place": "2"
  },
  {
    "meet_id": 256,
    "meet": "2026 WD Long Course March Meet",
    "date": "2026-03-21",
    "course": "LCM",
    "event": "200 Freestyle",
    "time": "2:41.45",
    "place": "8"
  },
  {
    "meet_id": 256,
    "meet": "2026 WD Long Course March Meet",
    "date": "2026-03-21",
    "course": "LCM",
    "event": "50 Backstroke",
    "time": "36.54",
    "place": "1"
  },
  {
    "meet_id": 256,
    "meet": "2026 WD Long Course March Meet",
    "date": "2026-03-21",
    "course": "LCM",
    "event": "100 Backstroke",
    "time": "1:21.92",
    "place": "6"
  },
  {
    "meet_id": 256,
    "meet": "2026 WD Long Course March Meet",
    "date": "2026-03-21",
    "course": "LCM",
    "event": "200 Backstroke",
    "time": "2:53.45",
    "place": "2"
  },
  {
    "meet_id": 265,
    "meet": "Club Time Trials April 2026",
    "date": "2026-04-20",
    "course": "SCM",
    "event": "50 Freestyle",
    "time": "30.48",
    "place": ""
  },
  {
    "meet_id": 265,
    "meet": "Club Time Trials April 2026",
    "date": "2026-04-20",
    "course": "SCM",
    "event": "100 Backstroke",
    "time": "1:20.39",
    "place": ""
  },
  {
    "meet_id": 265,
    "meet": "Club Time Trials April 2026",
    "date": "2026-04-20",
    "course": "SCM",
    "event": "200 IM",
    "time": "2:59.81",
    "place": ""
  },
  {
    "meet_id": 268,
    "meet": "Club Time Trials May 2026",
    "date": "2026-05-04",
    "course": "SCM",
    "event": "50 Backstroke",
    "time": "34.88",
    "place": ""
  },
  {
    "meet_id": 268,
    "meet": "Club Time Trials May 2026",
    "date": "2026-05-04",
    "course": "SCM",
    "event": "200 Breaststroke",
    "time": "3:27.09",
    "place": ""
  },
  {
    "meet_id": 268,
    "meet": "Club Time Trials May 2026",
    "date": "2026-05-04",
    "course": "SCM",
    "event": "100 IM",
    "time": "1:21.14",
    "place": ""
  },
  {
    "meet_id": 272,
    "meet": "2026 WD LC May AG Meet",
    "date": "2026-05-09",
    "course": "LCM",
    "event": "50 Freestyle",
    "time": "30.93",
    "place": "4"
  },
  {
    "meet_id": 272,
    "meet": "2026 WD LC May AG Meet",
    "date": "2026-05-09",
    "course": "LCM",
    "event": "50 Backstroke",
    "time": "35.28",
    "place": "3"
  },
  {
    "meet_id": 263,
    "meet": "Sl Development Meet 3 - 2026",
    "date": "2026-05-09",
    "course": "SCM",
    "event": "100 Freestyle",
    "time": "1:10.68",
    "place": "1"
  },
  {
    "meet_id": 263,
    "meet": "Sl Development Meet 3 - 2026",
    "date": "2026-05-09",
    "course": "SCM",
    "event": "100 Backstroke",
    "time": "1:17.37",
    "place": "1"
  }
]