[
  {
    "ath_id": null,
    "last": "Addison",
    "first": "Heidi",
    "gender": "F",
    "age": "13",
    "event": "50 Freestyle",
    "time": "32.23",
    "place": ""
  },
  {
    "ath_id": null,
    "last": "Addison",
    "first": "Heidi",
    "gender": "F",
    "age": "13",
    "event": "50 Backstroke",
    "time": "36.96",
    "place": ""
  },
  {
    "ath_id": null,
    "last": "Addison",
    "first": "Heidi",
    "gender": "F",
    "age": "13",
    "event": "50 Breaststroke",
    "time": "40.32",
    "place": ""
  },
  {
    "ath_id": null,
    "last": "Addison",
    "first": "Heidi",
    "gender": "F",
    "age": "13",
    "event": "50 Butterfly",
    "time": "37.09",
    "place": ""
  },
  {
    "ath_id": null,
    "last": "Addison",
    "first": "Isaac",
    "gender": "M",
    "age": "8",
    "event": "50 Freestyle",
    "time": "50.87",
    "place": ""
  },
  {
    "ath_id": null,
    "last": "Addison",
    "first": "Isaac",
    "gender": "M",
    "age": "8",
    "event": "50 Backstroke",
    "time": "54.27",
    "place": ""
  },
  {
    "ath_id": null,
    "last": "Addison",
    "first": "Isaac",
    "gender": "M",
    "age": "8",
    "event": "50 Breaststroke",
    "time": "1:00.54",
    "place": ""
  },
  {
    "ath_id": null,
    "last": "Addison",
    "first": "Isaac",
    "gender": "M",
    "age": "8",
    "event": "50 Butterfly",
    "time": "1:21.40",
    "place": ""
  },
  {
    "ath_id": null,
    "last": "Addison",
    "first": "Wendy",
    "gender": "F",
    "age": "10",
    "event": "50 Freestyle",
    "time": "37.21",
    "place": ""
  },
  {
    "ath_id": null,
    "last": "Addison",
    "first": "Wendy",
    "gender": "F",
    "age": "10",
    "event": "50 Backstroke",
    "time": "42.73",
    "place": ""
  },
  {
    "ath_id": null,
    "last": "Addison",
    "first": "Wendy",
    "gender": "F",
    "age": "10",
    "event": "50 Breaststroke",
    "time": "48.10",
    "place": ""
  },
  {
    "ath_id": null,
    "last": "Addison",
    "first": "Wendy",
    "gender": "F",
    "age": "10",
    "event": "50 Butterfly",
    "time": "40.81",
    "place": ""
  },
  {
    "ath_id": null,
    "last": "Black",
    "first": "Erin",
    "gender": "F",
    "age": "8",
    "event": "50 Backstroke",
    "time": "58.24",
    "place": ""
  },
  {
    "ath_id": null,
    "last": "Blackstock",
    "first": "Anna",
    "gender": "F",
    "age": "13",
    "event": "50 Backstroke",
    "time": "58.56",
    "place": ""
  },
  {
    "ath_id": null,
    "last": "Blackstock",
    "first": "James",
    "gender": "M",
    "age": "11",
    "event": "50 Backstroke",
    "time": "50.08",
    "place": ""
  },
  {
    "ath_id": null,
    "last": "Brown",
    "first": "Katie",
    "gender": "F",
    "age": "11",
    "event": "50 Freestyle",
    "time": "53.37",
    "place": ""
  },
  {
    "ath_id": null,
    "last": "Brown",
    "first": "Katie",
    "gender": "F",
    "age": "11",
    "event": "50 Backstroke",
    "time": "1:00.40",
    "place": ""
  },
  {
    "ath_id": null,
    "last": "Brown",
    "first": "Katie",
    "gender": "F",
    "age": "11",
    "event": "50 Breaststroke",
    "time": "1:05.86",
    "place": ""
  },
  {
    "ath_id": null,
    "last": "Brown",
    "first": "Katie",
    "gender": "F",
    "age": "11",
    "event": "50 Butterfly",
    "time": "1:07.76",
    "place": ""
  },
  {
    "ath_id": null,
    "last": "Buchan",
    "first": "Oliver",
    "gender": "M",
    "age": "11",
    "event": "50 Freestyle",
    "time": "35.10",
    "place": ""
  },
  {
    "ath_id": null,
    "last": "Buchan",
    "first": "Oliver",
    "gender": "M",
    "age": "11",
    "event": "50 Backstroke",
    "time": "38.15",
    "place": ""
  },
  {
    "ath_id": null,
    "last": "Buchan",
    "first": "Oliver",
    "gender": "M",
    "age": "11",
    "event": "50 Breaststroke",
    "time": "50.13",
    "place": ""
  },
  {
    "ath_id": null,
    "last": "Buchan",
    "first": "Oliver",
    "gender": "M",
    "age": "11",
    "event": "50 Butterfly",
    "time": "38.43",
    "place": ""
  },
  {
    "ath_id": null,
    "last": "Buchan",
    "first": "Tom",
    "gender": "M",
    "age": "8",
    "event": "50 Freestyle",
    "time": "39.24",
    "place": ""
  },
  {
    "ath_id": null,
    "last": "Buchan",
    "first": "Tom",
    "gender": "M",
    "age": "8",
    "event": "50 Backstroke",
    "time": "47.65",
    "place": ""
  },
  {
    "ath_id": null,
    "last": "Buchan",
    "first": "Tom",
    "gender": "M",
    "age": "8",
    "event": "50 Breaststroke",
    "time": "1:01.66",
    "place": ""
  },
  {
    "ath_id": null,
    "last": "Buchan",
    "first": "Tom",
    "gender": "M",
    "age": "8",
    "event": "50 Butterfly",
    "time": "45.78",
    "place": ""
  },
  {
    "ath_id": null,
    "last": "Callaghan",
    "first": "Locky",
    "gender": "M",
    "age": "9",
    "event": "50 Backstroke",
    "time": "1:06.48",
    "place": ""
  },
  {
    "ath_id": null,
    "last": "Callaghan",
    "first": "Millie",
    "gender": "F",
    "age": "13",
    "event": "50 Freestyle",
    "time": "41.00",
    "place": ""
  },
  {
    "ath_id": null,
    "last": "Callaghan",
    "first": "Millie",
    "gender": "F",
    "age": "13",
    "event": "50 Backstroke",
    "time": "44.39",
    "place": ""
  },
  {
    "ath_id": null,
    "last": "Callaghan",
    "first": "Millie",
    "gender": "F",
    "age": "13",
    "event": "50 Breaststroke",
    "time": "55.77",
    "place": ""
  },
  {
    "ath_id": null,
    "last": "Callaghan",
    "first": "Millie",
    "gender": "F",
    "age": "13",
    "event": "50 Butterfly",
    "time": "49.87",
    "place": ""
  },
  {
    "ath_id": null,
    "last": "Charlton",
    "first": "Sophie",
    "gender": "F",
    "age": "8",
    "event": "50 Backstroke",
    "time": "58.61",
    "place": ""
  },
  {
    "ath_id": null,
    "last": "Clark",
    "first": "James",
    "gender": "M",
    "age": "9",
    "event": "50 Freestyle",
    "time": "44.32",
    "place": ""
  },
  {
    "ath_id": null,
    "last": "Clark",
    "first": "James",
    "gender": "M",
    "age": "9",
    "event": "50 Backstroke",
    "time": "55.66",
    "place": ""
  },
  {
    "ath_id": null,
    "last": "Clark",
    "first": "James",
    "gender": "M",
    "age": "9",
    "event": "50 Breaststroke",
    "time": "59.91",
    "place": ""
  },
  {
    "ath_id": null,
    "last": "Clark",
    "first": "James",
    "gender": "M",
    "age": "9",
    "event": "50 Butterfly",
    "time": "1:03.20",
    "place": ""
  },
  {
    "ath_id": null,
    "last": "Clark",
    "first": "Matthew",
    "gender": "M",
    "age": "12",
    "event": "50 Freestyle",
    "time": "53.92",
    "place": ""
  },
  {
    "ath_id": null,
    "last": "Clark",
    "first": "Matthew",
    "gender": "M",
    "age": "12",
    "event": "50 Backstroke",
    "time": "1:00.25",
    "place": ""
  },
  {
    "ath_id": null,
    "last": "Clark",
    "first": "Matthew",
    "gender": "M",
    "age": "12",
    "event": "50 Breaststroke",
    "time": "1:10.76",
    "place": ""
  },
  {
    "ath_id": null,
    "last": "Clark",
    "first": "Matthew",
    "gender": "M",
    "age": "12",
    "event": "50 Butterfly",
    "time": "1:09.70",
    "place": ""
  },
  {
    "ath_id": null,
    "last": "Connor",
    "first": "Carys",
    "gender": "F",
    "age": "11",
    "event": "50 Freestyle",
    "time": "36.59",
    "place": ""
  },
  {
    "ath_id": null,
    "last": "Connor",
    "first": "Carys",
    "gender": "F",
    "age": "11",
    "event": "50 Backstroke",
    "time": "44.09",
    "place": ""
  },
  {
    "ath_id": null,
    "last": "Connor",
    "first": "Carys",
    "gender": "F",
    "age": "11",
    "event": "50 Breaststroke",
    "time": "48.71",
    "place": ""
  },
  {
    "ath_id": null,
    "last": "Connor",
    "first": "Carys",
    "gender": "F",
    "age": "11",
    "event": "50 Butterfly",
    "time": "46.89",
    "place": ""
  },
  {
    "ath_id": null,
    "last": "Connor",
    "first": "Isaac",
    "gender": "M",
    "age": "8",
    "event": "50 Backstroke",
    "time": "1:09.53",
    "place": ""
  },
  {
    "ath_id": null,
    "last": "Connor",
    "first": "Richard",
    "gender": "M",
    "age": "11",
    "event": "50 Freestyle",
    "time": "36.85",
    "place": ""
  },
  {
    "ath_id": null,
    "last": "Connor",
    "first": "Richard",
    "gender": "M",
    "age": "11",
    "event": "50 Backstroke",
    "time": "40.81",
    "place": ""
  },
  {
    "ath_id": null,
    "last": "Connor",
    "first": "Richard",
    "gender": "M",
    "age": "11",
    "event": "50 Breaststroke",
    "time": "56.65",
    "place": ""
  },
  {
    "ath_id": null,
    "last": "Connor",
    "first": "Richard",
    "gender": "M",
    "age": "11",
    "event": "50 Butterfly",
    "time": "42.24",
    "place": ""
  },
  {
    "ath_id": null,
    "last": "Easton",
    "first": "Joshua",
    "gender": "M",
    "age": "11",
    "event": "50 Freestyle",
    "time": "34.81",
    "place": ""
  },
  {
    "ath_id": null,
    "last": "Easton",
    "first": "Joshua",
    "gender": "M",
    "age": "11",
    "event": "50 Backstroke",
    "time": "40.59",
    "place": ""
  },
  {
    "ath_id": null,
    "last": "Easton",
    "first": "Joshua",
    "gender": "M",
    "age": "11",
    "event": "50 Breaststroke",
    "time": "45.00",
    "place": ""
  },
  {
    "ath_id": null,
    "last": "Easton",
    "first": "Joshua",
    "gender": "M",
    "age": "11",
    "event": "50 Butterfly",
    "time": "36.40",
    "place": ""
  },
  {
    "ath_id": null,
    "last": "Farrell",
    "first": "Rosie",
    "gender": "F",
    "age": "12",
    "event": "50 Freestyle",
    "time": "45.51",
    "place": ""
  },
  {
    "ath_id": null,
    "last": "Farrell",
    "first": "Rosie",
    "gender": "F",
    "age": "12",
    "event": "50 Backstroke",
    "time": "52.30",
    "place": ""
  },
  {
    "ath_id": null,
    "last": "Farrell",
    "first": "Rosie",
    "gender": "F",
    "age": "12",
    "event": "50 Breaststroke",
    "time": "54.21",
    "place": ""
  },
  {
    "ath_id": null,
    "last": "Farrell",
    "first": "Rosie",
    "gender": "F",
    "age": "12",
    "event": "50 Butterfly",
    "time": "55.22",
    "place": ""
  },
  {
    "ath_id": null,
    "last": "Ferguson",
    "first": "Callum",
    "gender": "M",
    "age": "11",
    "event": "50 Freestyle",
    "time": "39.34",
    "place": ""
  },
  {
    "ath_id": null,
    "last": "Ferguson",
    "first": "Callum",
    "gender": "M",
    "age": "11",
    "event": "50 Backstroke",
    "time": "49.07",
    "place": ""
  },
  {
    "ath_id": null,
    "last": "Ferguson",
    "first": "Callum",
    "gender": "M",
    "age": "11",
    "event": "50 Breaststroke",
    "time": "45.72",
    "place": ""
  },
  {
    "ath_id": null,
    "last": "Ferguson",
    "first": "Callum",
    "gender": "M",
    "age": "11",
    "event": "50 Butterfly",
    "time": "44.98",
    "place": ""
  },
  {
    "ath_id": null,
    "last": "Fletcher",
    "first": "Connie",
    "gender": "F",
    "age": "11",
    "event": "50 Freestyle",
    "time": "54.83",
    "place": ""
  },
  {
    "ath_id": null,
    "last": "Fletcher",
    "first": "Connie",
    "gender": "F",
    "age": "11",
    "event": "50 Backstroke",
    "time": "53.86",
    "place": ""
  },
  {
    "ath_id": null,
    "last": "Fletcher",
    "first": "Connie",
    "gender": "F",
    "age": "11",
    "event": "50 Breaststroke",
    "time": "1:06.68",
    "place": ""
  },
  {
    "ath_id": null,
    "last": "Fletcher",
    "first": "Connie",
    "gender": "F",
    "age": "11",
    "event": "50 Butterfly",
    "time": "1:02.85",
    "place": ""
  },
  {
    "ath_id": null,
    "last": "Forshaw",
    "first": "Arya",
    "gender": "F",
    "age": "12",
    "event": "50 Freestyle",
    "time": "45.87",
    "place": ""
  },
  {
    "ath_id": null,
    "last": "Forshaw",
    "first": "Arya",
    "gender": "F",
    "age": "12",
    "event": "50 Backstroke",
    "time": "54.06",
    "place": ""
  },
  {
    "ath_id": null,
    "last": "Forshaw",
    "first": "Arya",
    "gender": "F",
    "age": "12",
    "event": "50 Breaststroke",
    "time": "59.31",
    "place": ""
  },
  {
    "ath_id": null,
    "last": "Forshaw",
    "first": "Arya",
    "gender": "F",
    "age": "12",
    "event": "50 Butterfly",
    "time": "57.65",
    "place": ""
  },
  {
    "ath_id": null,
    "last": "Forshaw",
    "first": "Kai",
    "gender": "M",
    "age": "9",
    "event": "50 Backstroke",
    "time": "1:12.46",
    "place": ""
  },
  {
    "ath_id": null,
    "last": "Franchuk",
    "first": "Maksym",
    "gender": "M",
    "age": "12",
    "event": "50 Backstroke",
    "time": "1:06.91",
    "place": ""
  },
  {
    "ath_id": null,
    "last": "Gilchrist",
    "first": "Campbell",
    "gender": "M",
    "age": "10",
    "event": "50 Freestyle",
    "time": "40.73",
    "place": ""
  },
  {
    "ath_id": null,
    "last": "Gilchrist",
    "first": "Campbell",
    "gender": "M",
    "age": "10",
    "event": "50 Backstroke",
    "time": "45.13",
    "place": ""
  },
  {
    "ath_id": null,
    "last": "Gilchrist",
    "first": "Campbell",
    "gender": "M",
    "age": "10",
    "event": "50 Breaststroke",
    "time": "1:03.23",
    "place": ""
  },
  {
    "ath_id": null,
    "last": "Gilchrist",
    "first": "Campbell",
    "gender": "M",
    "age": "10",
    "event": "50 Butterfly",
    "time": "53.24",
    "place": ""
  },
  {
    "ath_id": null,
    "last": "Halforty",
    "first": "John",
    "gender": "M",
    "age": "11",
    "event": "50 Freestyle",
    "time": "48.91",
    "place": ""
  },
  {
    "ath_id": null,
    "last": "Halforty",
    "first": "John",
    "gender": "M",
    "age": "11",
    "event": "50 Backstroke",
    "time": "59.74",
    "place": ""
  },
  {
    "ath_id": null,
    "last": "Halforty",
    "first": "John",
    "gender": "M",
    "age": "11",
    "event": "50 Breaststroke",
    "time": "1:06.02",
    "place": ""
  },
  {
    "ath_id": null,
    "last": "Halforty",
    "first": "John",
    "gender": "M",
    "age": "11",
    "event": "50 Butterfly",
    "time": "59.74",
    "place": ""
  },
  {
    "ath_id": null,
    "last": "Hamilton",
    "first": "Keiran",
    "gender": "M",
    "age": "9",
    "event": "50 Backstroke",
    "time": "1:02.13",
    "place": ""
  },
  {
    "ath_id": null,
    "last": "Hamilton",
    "first": "Leah",
    "gender": "F",
    "age": "12",
    "event": "50 Freestyle",
    "time": "38.45",
    "place": ""
  },
  {
    "ath_id": null,
    "last": "Hamilton",
    "first": "Leah",
    "gender": "F",
    "age": "12",
    "event": "50 Backstroke",
    "time": "43.49",
    "place": ""
  },
  {
    "ath_id": null,
    "last": "Hamilton",
    "first": "Leah",
    "gender": "F",
    "age": "12",
    "event": "50 Breaststroke",
    "time": "48.50",
    "place": ""
  },
  {
    "ath_id": null,
    "last": "Hamilton",
    "first": "Mirren",
    "gender": "F",
    "age": "15",
    "event": "50 Freestyle",
    "time": "35.66",
    "place": ""
  },
  {
    "ath_id": null,
    "last": "Hamilton",
    "first": "Mirren",
    "gender": "F",
    "age": "15",
    "event": "50 Backstroke",
    "time": "40.25",
    "place": ""
  },
  {
    "ath_id": null,
    "last": "Hamilton",
    "first": "Mirren",
    "gender": "F",
    "age": "15",
    "event": "50 Breaststroke",
    "time": "44.54",
    "place": ""
  },
  {
    "ath_id": null,
    "last": "Hamilton",
    "first": "Mirren",
    "gender": "F",
    "age": "15",
    "event": "50 Butterfly",
    "time": "40.70",
    "place": ""
  },
  {
    "ath_id": null,
    "last": "Harkin",
    "first": "Grace",
    "gender": "F",
    "age": "10",
    "event": "50 Freestyle",
    "time": "51.73",
    "place": ""
  },
  {
    "ath_id": null,
    "last": "Harkin",
    "first": "Grace",
    "gender": "F",
    "age": "10",
    "event": "50 Backstroke",
    "time": "1:03.18",
    "place": ""
  },
  {
    "ath_id": null,
    "last": "Harkin",
    "first": "Grace",
    "gender": "F",
    "age": "10",
    "event": "50 Breaststroke",
    "time": "1:13.36",
    "place": ""
  },
  {
    "ath_id": null,
    "last": "Harkin",
    "first": "Grace",
    "gender": "F",
    "age": "10",
    "event": "50 Butterfly",
    "time": "1:05.18",
    "place": ""
  },
  {
    "ath_id": null,
    "last": "Harkin",
    "first": "Owen",
    "gender": "M",
    "age": "13",
    "event": "50 Freestyle",
    "time": "48.64",
    "place": ""
  },
  {
    "ath_id": null,
    "last": "Harkin",
    "first": "Owen",
    "gender": "M",
    "age": "13",
    "event": "50 Backstroke",
    "time": "1:00.36",
    "place": ""
  },
  {
    "ath_id": null,
    "last": "Harkin",
    "first": "Owen",
    "gender": "M",
    "age": "13",
    "event": "50 Breaststroke",
    "time": "58.11",
    "place": ""
  },
  {
    "ath_id": null,
    "last": "Harkin",
    "first": "Owen",
    "gender": "M",
    "age": "13",
    "event": "50 Butterfly",
    "time": "1:00.36",
    "place": ""
  },
  {
    "ath_id": null,
    "last": "Innes",
    "first": "Sofi",
    "gender": "F",
    "age": "12",
    "event": "50 Freestyle",
    "time": "33.24",
    "place": ""
  },
  {
    "ath_id": null,
    "last": "Jones",
    "first": "Sam",
    "gender": "M",
    "age": "12",
    "event": "50 Freestyle",
    "time": "36.86",
    "place": ""
  },
  {
    "ath_id": null,
    "last": "Jones",
    "first": "Sam",
    "gender": "M",
    "age": "12",
    "event": "50 Backstroke",
    "time": "43.99",
    "place": ""
  },
  {
    "ath_id": null,
    "last": "Jones",
    "first": "Sam",
    "gender": "M",
    "age": "12",
    "event": "50 Breaststroke",
    "time": "47.69",
    "place": ""
  },
  {
    "ath_id": null,
    "last": "Jones",
    "first": "Sam",
    "gender": "M",
    "age": "12",
    "event": "50 Butterfly",
    "time": "41.61",
    "place": ""
  },
  {
    "ath_id": null,
    "last": "Kulkarni",
    "first": "Arjun",
    "gender": "M",
    "age": "12",
    "event": "50 Freestyle",
    "time": "43.70",
    "place": ""
  },
  {
    "ath_id": null,
    "last": "Kulkarni",
    "first": "Arjun",
    "gender": "M",
    "age": "12",
    "event": "50 Backstroke",
    "time": "57.82",
    "place": ""
  },
  {
    "ath_id": null,
    "last": "Kulkarni",
    "first": "Arjun",
    "gender": "M",
    "age": "12",
    "event": "50 Breaststroke",
    "time": "59.96",
    "place": ""
  },
  {
    "ath_id": null,
    "last": "Kulkarni",
    "first": "Arjun",
    "gender": "M",
    "age": "12",
    "event": "50 Butterfly",
    "time": "50.39",
    "place": ""
  },
  {
    "ath_id": null,
    "last": "Lorimer",
    "first": "Hamish",
    "gender": "M",
    "age": "10",
    "event": "50 Freestyle",
    "time": "1:10.65",
    "place": ""
  },
  {
    "ath_id": null,
    "last": "Lorimer",
    "first": "Hamish",
    "gender": "M",
    "age": "10",
    "event": "50 Backstroke",
    "time": "1:13.98",
    "place": ""
  },
  {
    "ath_id": null,
    "last": "Lorimer",
    "first": "Hamish",
    "gender": "M",
    "age": "10",
    "event": "50 Breaststroke",
    "time": "1:15.72",
    "place": ""
  },
  {
    "ath_id": null,
    "last": "Lorimer",
    "first": "Hamish",
    "gender": "M",
    "age": "10",
    "event": "50 Butterfly",
    "time": "1:19.22",
    "place": ""
  },
  {
    "ath_id": null,
    "last": "Marshall",
    "first": "Lauren",
    "gender": "F",
    "age": "11",
    "event": "50 Freestyle",
    "time": "46.35",
    "place": ""
  },
  {
    "ath_id": null,
    "last": "Marshall",
    "first": "Lauren",
    "gender": "F",
    "age": "11",
    "event": "50 Backstroke",
    "time": "53.35",
    "place": ""
  },
  {
    "ath_id": null,
    "last": "Marshall",
    "first": "Lauren",
    "gender": "F",
    "age": "11",
    "event": "50 Breaststroke",
    "time": "1:00.04",
    "place": ""
  },
  {
    "ath_id": null,
    "last": "Marshall",
    "first": "Lauren",
    "gender": "F",
    "age": "11",
    "event": "50 Butterfly",
    "time": "1:01.16",
    "place": ""
  },
  {
    "ath_id": null,
    "last": "Martin Barrera",
    "first": "Ilithyia",
    "gender": "F",
    "age": "11",
    "event": "50 Freestyle",
    "time": "43.35",
    "place": ""
  },
  {
    "ath_id": null,
    "last": "Martin Barrera",
    "first": "Ilithyia",
    "gender": "F",
    "age": "11",
    "event": "50 Backstroke",
    "time": "53.92",
    "place": ""
  },
  {
    "ath_id": null,
    "last": "Martin Barrera",
    "first": "Ilithyia",
    "gender": "F",
    "age": "11",
    "event": "50 Breaststroke",
    "time": "59.63",
    "place": ""
  },
  {
    "ath_id": null,
    "last": "Martin Barrera",
    "first": "Ilithyia",
    "gender": "F",
    "age": "11",
    "event": "50 Butterfly",
    "time": "50.92",
    "place": ""
  },
  {
    "ath_id": null,
    "last": "Mcauley",
    "first": "Cailyn",
    "gender": "F",
    "age": "14",
    "event": "50 Freestyle",
    "time": "34.20",
    "place": ""
  },
  {
    "ath_id": null,
    "last": "Mcauley",
    "first": "Cailyn",
    "gender": "F",
    "age": "14",
    "event": "50 Backstroke",
    "time": "38.78",
    "place": ""
  },
  {
    "ath_id": null,
    "last": "Mcauley",
    "first": "Cailyn",
    "gender": "F",
    "age": "14",
    "event": "50 Breaststroke",
    "time": "43.75",
    "place": ""
  },
  {
    "ath_id": null,
    "last": "Mcauley",
    "first": "Cailyn",
    "gender": "F",
    "age": "14",
    "event": "50 Butterfly",
    "time": "34.21",
    "place": ""
  },
  {
    "ath_id": null,
    "last": "McCarthy",
    "first": "Alexis",
    "gender": "F",
    "age": "12",
    "event": "50 Freestyle",
    "time": "35.56",
    "place": ""
  },
  {
    "ath_id": null,
    "last": "McMillan",
    "first": "Skye",
    "gender": "F",
    "age": "8",
    "event": "50 Backstroke",
    "time": "1:07.49",
    "place": ""
  },
  {
    "ath_id": null,
    "last": "McNaughton",
    "first": "Cole",
    "gender": "M",
    "age": "14",
    "event": "50 Freestyle",
    "time": "35.27",
    "place": ""
  },
  {
    "ath_id": null,
    "last": "McNaughton",
    "first": "Cole",
    "gender": "M",
    "age": "14",
    "event": "50 Backstroke",
    "time": "41.04",
    "place": ""
  },
  {
    "ath_id": null,
    "last": "McNaughton",
    "first": "Cole",
    "gender": "M",
    "age": "14",
    "event": "50 Breaststroke",
    "time": "50.14",
    "place": ""
  },
  {
    "ath_id": null,
    "last": "McNaughton",
    "first": "Cole",
    "gender": "M",
    "age": "14",
    "event": "50 Butterfly",
    "time": "38.77",
    "place": ""
  },
  {
    "ath_id": null,
    "last": "Meikle",
    "first": "Chloe",
    "gender": "F",
    "age": "11",
    "event": "50 Freestyle",
    "time": "51.94",
    "place": ""
  },
  {
    "ath_id": null,
    "last": "Meikle",
    "first": "Chloe",
    "gender": "F",
    "age": "11",
    "event": "50 Backstroke",
    "time": "58.34",
    "place": ""
  },
  {
    "ath_id": null,
    "last": "Meikle",
    "first": "Chloe",
    "gender": "F",
    "age": "11",
    "event": "50 Breaststroke",
    "time": "59.92",
    "place": ""
  },
  {
    "ath_id": null,
    "last": "Meikle",
    "first": "Chloe",
    "gender": "F",
    "age": "11",
    "event": "50 Butterfly",
    "time": "1:01.33",
    "place": ""
  },
  {
    "ath_id": null,
    "last": "Neeson",
    "first": "Zakk",
    "gender": "M",
    "age": "13",
    "event": "50 Freestyle",
    "time": "30.49",
    "place": ""
  },
  {
    "ath_id": null,
    "last": "Neeson",
    "first": "Zakk",
    "gender": "M",
    "age": "13",
    "event": "50 Backstroke",
    "time": "35.73",
    "place": ""
  },
  {
    "ath_id": null,
    "last": "Neeson",
    "first": "Zakk",
    "gender": "M",
    "age": "13",
    "event": "50 Breaststroke",
    "time": "37.18",
    "place": ""
  },
  {
    "ath_id": null,
    "last": "Neeson",
    "first": "Zakk",
    "gender": "M",
    "age": "13",
    "event": "50 Butterfly",
    "time": "34.20",
    "place": ""
  },
  {
    "ath_id": null,
    "last": "Noble",
    "first": "Cameron",
    "gender": "M",
    "age": "11",
    "event": "50 Freestyle",
    "time": "41.02",
    "place": ""
  },
  {
    "ath_id": null,
    "last": "Noble",
    "first": "Cameron",
    "gender": "M",
    "age": "11",
    "event": "50 Backstroke",
    "time": "45.37",
    "place": ""
  },
  {
    "ath_id": null,
    "last": "Noble",
    "first": "Cameron",
    "gender": "M",
    "age": "11",
    "event": "50 Breaststroke",
    "time": "58.70",
    "place": ""
  },
  {
    "ath_id": null,
    "last": "Noble",
    "first": "Cameron",
    "gender": "M",
    "age": "11",
    "event": "50 Butterfly",
    "time": "51.78",
    "place": ""
  },
  {
    "ath_id": null,
    "last": "Nutt",
    "first": "Kaitlin",
    "gender": "F",
    "age": "25",
    "event": "50 Freestyle",
    "time": "1:03.56",
    "place": ""
  },
  {
    "ath_id": null,
    "last": "Nutt",
    "first": "Kaitlin",
    "gender": "F",
    "age": "25",
    "event": "50 Backstroke",
    "time": "1:17.55",
    "place": ""
  },
  {
    "ath_id": null,
    "last": "Nutt",
    "first": "Kaitlin",
    "gender": "F",
    "age": "25",
    "event": "50 Breaststroke",
    "time": "1:24.66",
    "place": ""
  },
  {
    "ath_id": null,
    "last": "Nutt",
    "first": "Kaitlin",
    "gender": "F",
    "age": "25",
    "event": "50 Butterfly",
    "time": "1:09.03",
    "place": ""
  },
  {
    "ath_id": null,
    "last": "Perrie",
    "first": "Sam",
    "gender": "M",
    "age": "14",
    "event": "50 Freestyle",
    "time": "30.20",
    "place": ""
  },
  {
    "ath_id": null,
    "last": "Perrie",
    "first": "Sam",
    "gender": "M",
    "age": "14",
    "event": "50 Backstroke",
    "time": "37.09",
    "place": ""
  },
  {
    "ath_id": null,
    "last": "Perrie",
    "first": "Sam",
    "gender": "M",
    "age": "14",
    "event": "50 Breaststroke",
    "time": "43.41",
    "place": ""
  },
  {
    "ath_id": null,
    "last": "Perrie",
    "first": "Sam",
    "gender": "M",
    "age": "14",
    "event": "50 Butterfly",
    "time": "32.55",
    "place": ""
  },
  {
    "ath_id": null,
    "last": "Scott",
    "first": "Cole",
    "gender": "M",
    "age": "13",
    "event": "50 Freestyle",
    "time": "33.13",
    "place": ""
  },
  {
    "ath_id": null,
    "last": "Scott",
    "first": "Cole",
    "gender": "M",
    "age": "13",
    "event": "50 Backstroke",
    "time": "39.69",
    "place": ""
  },
  {
    "ath_id": null,
    "last": "Scott",
    "first": "Cole",
    "gender": "M",
    "age": "13",
    "event": "50 Breaststroke",
    "time": "43.35",
    "place": ""
  },
  {
    "ath_id": null,
    "last": "Scott",
    "first": "Cole",
    "gender": "M",
    "age": "13",
    "event": "50 Butterfly",
    "time": "36.51",
    "place": ""
  },
  {
    "ath_id": null,
    "last": "Smith",
    "first": "Noah",
    "gender": "M",
    "age": "13",
    "event": "50 Freestyle",
    "time": "40.43",
    "place": ""
  },
  {
    "ath_id": null,
    "last": "Smith",
    "first": "Noah",
    "gender": "M",
    "age": "13",
    "event": "50 Backstroke",
    "time": "48.52",
    "place": ""
  },
  {
    "ath_id": null,
    "last": "Smith",
    "first": "Noah",
    "gender": "M",
    "age": "13",
    "event": "50 Breaststroke",
    "time": "47.59",
    "place": ""
  },
  {
    "ath_id": null,
    "last": "Smith",
    "first": "Noah",
    "gender": "M",
    "age": "13",
    "event": "50 Butterfly",
    "time": "46.08",
    "place": ""
  },
  {
    "ath_id": null,
    "last": "Smith",
    "first": "Roman",
    "gender": "M",
    "age": "9",
    "event": "50 Freestyle",
    "time": "42.18",
    "place": ""
  },
  {
    "ath_id": null,
    "last": "Smith",
    "first": "Roman",
    "gender": "M",
    "age": "9",
    "event": "50 Backstroke",
    "time": "47.21",
    "place": ""
  },
  {
    "ath_id": null,
    "last": "Smith",
    "first": "Roman",
    "gender": "M",
    "age": "9",
    "event": "50 Breaststroke",
    "time": "55.35",
    "place": ""
  },
  {
    "ath_id": null,
    "last": "Smith",
    "first": "Roman",
    "gender": "M",
    "age": "9",
    "event": "50 Butterfly",
    "time": "58.96",
    "place": ""
  },
  {
    "ath_id": null,
    "last": "Soper",
    "first": "Darcy",
    "gender": "F",
    "age": "10",
    "event": "50 Freestyle",
    "time": "47.98",
    "place": ""
  },
  {
    "ath_id": null,
    "last": "Soper",
    "first": "Darcy",
    "gender": "F",
    "age": "10",
    "event": "50 Backstroke",
    "time": "50.43",
    "place": ""
  },
  {
    "ath_id": null,
    "last": "Soper",
    "first": "Darcy",
    "gender": "F",
    "age": "10",
    "event": "50 Breaststroke",
    "time": "57.58",
    "place": ""
  },
  {
    "ath_id": null,
    "last": "Soper",
    "first": "Darcy",
    "gender": "F",
    "age": "10",
    "event": "50 Butterfly",
    "time": "55.27",
    "place": ""
  },
  {
    "ath_id": null,
    "last": "Soper",
    "first": "Lacey",
    "gender": "F",
    "age": "13",
    "event": "50 Freestyle",
    "time": "42.08",
    "place": ""
  },
  {
    "ath_id": null,
    "last": "Soper",
    "first": "Lacey",
    "gender": "F",
    "age": "13",
    "event": "50 Backstroke",
    "time": "46.89",
    "place": ""
  },
  {
    "ath_id": null,
    "last": "Soper",
    "first": "Lacey",
    "gender": "F",
    "age": "13",
    "event": "50 Breaststroke",
    "time": "52.47",
    "place": ""
  },
  {
    "ath_id": null,
    "last": "Soper",
    "first": "Lacey",
    "gender": "F",
    "age": "13",
    "event": "50 Butterfly",
    "time": "49.45",
    "place": ""
  },
  {
    "ath_id": null,
    "last": "Stevenson",
    "first": "Skye",
    "gender": "F",
    "age": "11",
    "event": "50 Freestyle",
    "time": "45.77",
    "place": ""
  },
  {
    "ath_id": null,
    "last": "Stevenson",
    "first": "Skye",
    "gender": "F",
    "age": "11",
    "event": "50 Backstroke",
    "time": "53.58",
    "place": ""
  },
  {
    "ath_id": null,
    "last": "Stevenson",
    "first": "Skye",
    "gender": "F",
    "age": "11",
    "event": "50 Breaststroke",
    "time": "54.32",
    "place": ""
  },
  {
    "ath_id": null,
    "last": "Stevenson",
    "first": "Skye",
    "gender": "F",
    "age": "11",
    "event": "50 Butterfly",
    "time": "49.17",
    "place": ""
  },
  {
    "ath_id": null,
    "last": "Stone",
    "first": "Jessica",
    "gender": "F",
    "age": "11",
    "event": "50 Freestyle",
    "time": "40.99",
    "place": ""
  },
  {
    "ath_id": null,
    "last": "Stone",
    "first": "Jessica",
    "gender": "F",
    "age": "11",
    "event": "50 Backstroke",
    "time": "50.09",
    "place": ""
  },
  {
    "ath_id": null,
    "last": "Stone",
    "first": "Jessica",
    "gender": "F",
    "age": "11",
    "event": "50 Breaststroke",
    "time": "54.83",
    "place": ""
  },
  {
    "ath_id": null,
    "last": "Stone",
    "first": "Jessica",
    "gender": "F",
    "age": "11",
    "event": "50 Butterfly",
    "time": "50.50",
    "place": ""
  },
  {
    "ath_id": null,
    "last": "Thompson",
    "first": "Amy",
    "gender": "F",
    "age": "9",
    "event": "50 Freestyle",
    "time": "52.96",
    "place": ""
  },
  {
    "ath_id": null,
    "last": "Thompson",
    "first": "Amy",
    "gender": "F",
    "age": "9",
    "event": "50 Backstroke",
    "time": "1:04.33",
    "place": ""
  },
  {
    "ath_id": null,
    "last": "Thompson",
    "first": "Amy",
    "gender": "F",
    "age": "9",
    "event": "50 Breaststroke",
    "time": "1:06.03",
    "place": ""
  },
  {
    "ath_id": null,
    "last": "Thompson",
    "first": "Amy",
    "gender": "F",
    "age": "9",
    "event": "50 Butterfly",
    "time": "1:04.98",
    "place": ""
  },
  {
    "ath_id": null,
    "last": "Thompson",
    "first": "Emma",
    "gender": "F",
    "age": "10",
    "event": "50 Freestyle",
    "time": "37.27",
    "place": ""
  },
  {
    "ath_id": null,
    "last": "Thompson",
    "first": "Emma",
    "gender": "F",
    "age": "10",
    "event": "50 Backstroke",
    "time": "45.02",
    "place": ""
  },
  {
    "ath_id": null,
    "last": "Thompson",
    "first": "Emma",
    "gender": "F",
    "age": "10",
    "event": "50 Breaststroke",
    "time": "48.07",
    "place": ""
  },
  {
    "ath_id": null,
    "last": "Thompson",
    "first": "Emma",
    "gender": "F",
    "age": "10",
    "event": "50 Butterfly",
    "time": "43.74",
    "place": ""
  },
  {
    "ath_id": null,
    "last": "Wayt",
    "first": "Quinn",
    "gender": "F",
    "age": "11",
    "event": "50 Freestyle",
    "time": "40.64",
    "place": ""
  },
  {
    "ath_id": null,
    "last": "Wayt",
    "first": "Quinn",
    "gender": "F",
    "age": "11",
    "event": "50 Backstroke",
    "time": "47.49",
    "place": ""
  },
  {
    "ath_id": null,
    "last": "Wayt",
    "first": "Quinn",
    "gender": "F",
    "age": "11",
    "event": "50 Breaststroke",
    "time": "54.44",
    "place": ""
  },
  {
    "ath_id": null,
    "last": "Wayt",
    "first": "Quinn",
    "gender": "F",
    "age": "11",
    "event": "50 Butterfly",
    "time": "50.48",
    "place": ""
  },
  {
    "ath_id": null,
    "last": "Young",
    "first": "Grace",
    "gender": "F",
    "age": "12",
    "event": "50 Freestyle",
    "time": "40.58",
    "place": ""
  },
  {
    "ath_id": null,
    "last": "Young",
    "first": "Grace",
    "gender": "F",
    "age": "12",
    "event": "50 Backstroke",
    "time": "55.12",
    "place": ""
  },
  {
    "ath_id": null,
    "last": "Young",
    "first": "Grace",
    "gender": "F",
    "age": "12",
    "event": "50 Breaststroke",
    "time": "59.04",
    "place": ""
  },
  {
    "ath_id": null,
    "last": "Young",
    "first": "Grace",
    "gender": "F",
    "age": "12",
    "event": "50 Butterfly",
    "time": "52.49",
    "place": ""
  },
  {
    "ath_id": null,
    "last": "Young",
    "first": "Leila",
    "gender": "F",
    "age": "10",
    "event": "50 Freestyle",
    "time": "52.09",
    "place": ""
  },
  {
    "ath_id": null,
    "last": "Young",
    "first": "Leila",
    "gender": "F",
    "age": "10",
    "event": "50 Backstroke",
    "time": "54.04",
    "place": ""
  },
  {
    "ath_id": null,
    "last": "Young",
    "first": "Leila",
    "gender": "F",
    "age": "10",
    "event": "50 Butterfly",
    "time": "59.68",
    "place": ""
  }
]